{
  "forbidden_flow_audit_id": "ffa_20260601_0001",
  "workstream": "budget/audit-trail",
  "artifact_id": "budget_audit_trail_docs_packet",
  "implementation_code_changed": false,
  "src_changed": false,
  "app_changed": false,
  "components_changed": false,
  "budget_engine_changed": false,
  "pricing_rule_changed": false,
  "budget_estimate_line_generated": false,
  "method_spec_implementation_changed": false,
  "raw_candidate_implementation_changed": false,
  "output_documents_implementation_changed": false,
  "renderer_runtime_changed": false,
  "formal_price_generated": false,
  "formal_quote_generated": false,
  "db_supabase_touched": false,
  "payment_touched": false,
  "ai_api_touched": false,
  "n8n_runtime_touched": false,
  "secrets_touched": false,
  "integration_harness_started": false,
  "result": "pass_docs_only",
  "created_at": "2026-06-01T00:00:00+08:00"
}
